thystreet/__init__.py
thystreet/api_client.py
thystreet/configuration.py
thystreet/exceptions.py
thystreet/model_utils.py
thystreet/rest.py
thystreet/api/__init__.py
thystreet/api/device_api.py
thystreet/apis/__init__.py
thystreet/model/__init__.py
thystreet/model/device_status_dto.py
thystreet/models/__init__.py
thystreet-0.0.1.dist-info/METADATA
thystreet-0.0.1.dist-info/WHEEL
thystreet-0.0.1.dist-info/top_level.txt
thystreet-0.0.1.dist-info/RECORD
